tink_python_api_types/__init__.py
tink_python_api_types/account.py
tink_python_api_types/common.py
tink_python_api_types/transaction.py
tink_python_api_types-0.0.13.dist-info/METADATA
tink_python_api_types-0.0.13.dist-info/WHEEL
tink_python_api_types-0.0.13.dist-info/licenses/LICENSE
tink_python_api_types-0.0.13.dist-info/RECORD
