Metadata-Version: 2.4
Name: tink-python-api-types
Version: 0.0.13
Summary: Python types for the tink API
Author-email: José Ignacio Amelivia Santiago <hello@namelivia.com>
License-File: LICENSE
Classifier: Development Status :: 5 - Production/Stable
Classifier: Intended Audience :: Developers
Classifier: License :: OSI Approved :: MIT License
Classifier: Programming Language :: Python :: 3.8
Classifier: Programming Language :: Python :: 3.9
Classifier: Programming Language :: Python :: 3.10
Classifier: Programming Language :: Python :: 3.11
Classifier: Topic :: Software Development :: Build Tools
Requires-Python: <=3.11,>=3.8
Requires-Dist: dacite
